{
    "message": "success",
    "stations": [
        {
            "AQI": 17,
            "CO": 0.156,
            "NO2": 17.574,
            "OZONE": 17.341,
            "PM10": 10.041,
            "PM25": 2.1,
            "SO2": 0.346,
            "aqiInfo": {
                "category": "Good",
                "concentration": 17.574,
                "pollutant": "NO2"
            },
            "city": "Toulouse",
            "countryCode": "FR",
            "division": "Haute-Garonne",
            "lat": 43.556374,
            "lng": 1.403964,
            "placeName": "Avenue de Larrieu",
            "postalCode": "31100",
            "state": "Occitanie",
            "updatedAt": "2023-09-22T06:00:00.000Z"
        }
    ]
}
